ipcq/__init__.py
ipcq/client.py
ipcq/ipcq.py
ipcq/server.py
ipcq-1.1.2.dist-info/LICENSE
ipcq-1.1.2.dist-info/WHEEL
ipcq-1.1.2.dist-info/METADATA
ipcq-1.1.2.dist-info/RECORD
