Metadata-Version: 2.1
Name: ipcq
Version: 1.1.2
Summary: 
Home-page: https://github.com/changyuheng/ipcq
Author: Henry Chang
Author-email: mr.changyuheng@gmail.com
Requires-Python: >=3.6,<4.0
Classifier: Programming Language :: Python :: 3
Classifier: Programming Language :: Python :: 3.6
Classifier: Programming Language :: Python :: 3.7
Classifier: Programming Language :: Python :: 3.8
